anyhttp/__init__.py
anyhttp/py33_clients.py
anyhttp-0.1.dist-info/LICENSE
anyhttp-0.1.dist-info/METADATA
anyhttp-0.1.dist-info/WHEEL
anyhttp-0.1.dist-info/dependency_links.txt
anyhttp-0.1.dist-info/top_level.txt
anyhttp-0.1.dist-info/version.txt
anyhttp-0.1.dist-info/RECORD
