Metadata-Version: 2.1
Name: anyhttp
Version: 0.1
Summary: Generic interface to access HTTP clients
Home-page: UNKNOWN
Maintainer: John Vandenberg
Maintainer-email: jayvdb@gmail.com
License: MIT License
Platform: UNKNOWN
Classifier: Topic :: Internet :: WWW/HTTP
Classifier: License :: OSI Approved :: MIT License
Classifier: Development Status :: 3 - Alpha
Classifier: Operating System :: OS Independent
Classifier: Intended Audience :: Developers
Classifier: Environment :: Console
Classifier: Programming Language :: Python :: 2.7
Classifier: Programming Language :: Python :: 3.3
Classifier: Programming Language :: Python :: 3.4
